seamlessf5/__init__.py
seamlessf5/albacore_hooks.py
seamlessf5/single2multi_hooks.py
seamlessf5-0.2.dist-info/LICENSE.txt
seamlessf5-0.2.dist-info/METADATA
seamlessf5-0.2.dist-info/WHEEL
seamlessf5-0.2.dist-info/entry_points.txt
seamlessf5-0.2.dist-info/top_level.txt
seamlessf5-0.2.dist-info/RECORD
