Metadata-Version: 2.1
Name: seamlessf5
Version: 0.2
Summary: Helpers for smoother transitioning to multi-read FAST5 files
Home-page: https://github.com/hyeshik/seamlessf5
Author: Hyeshik Chang
Author-email: hyeshik@snu.ac.kr
License: MIT
Download-URL: https://github.com/hyeshik/seamlessf5/releases
Keywords: nanopore,fast5,converter,wrapper
Platform: UNKNOWN
Classifier: Development Status :: 3 - Alpha
Classifier: Environment :: Console
Classifier: Intended Audience :: Science/Research
Classifier: Intended Audience :: Healthcare Industry
Classifier: License :: OSI Approved :: MIT License
Classifier: Operating System :: POSIX
Classifier: Programming Language :: Python
Classifier: Topic :: Scientific/Engineering :: Bio-Informatics
Requires-Dist: h5py (>=2.9.0)
Requires-Dist: ont-fast5-api (>=1.0.1)
Requires-Dist: progressbar33 (>=2.4)
